{
  "metadata": {
    "run_id": "cnn_fedprox_non-iid_r10_e2_mu0.005_seed123",
    "model": "CNN",
    "setting": "FedProx",
    "data_mode": "Non-IID",
    "snr_db": 10,
    "seed": 123,
    "local_epochs": 2,
    "global_rounds": 10,
    "mu": 0.005,
    "lr": 0.001,
    "batch_size": 32,
    "config_path": "/Users/chaitu/Desktop/Wireless paper/Project/experiment_config.json",
    "config_sha256": "8562342df0c8bfb2fed2f8198a96851a9b01057c32fc3f455e88d67104a99cb7",
    "git_commit": "27e59aad6cb238a367ea43446014fd8cf2cd07b3",
    "python_version": "3.12.4",
    "torch_version": "2.11.0",
    "device": "mps",
    "platform": "macOS-26.3.1-arm64-arm-64bit",
    "extra": {
      "num_clients": 5,
      "name": "FedProx Non-IID"
    }
  },
  "started_at": 1776296647.905889,
  "history": [
    {
      "step_kind": "round",
      "step_index": 1,
      "nmse_db": -13.834186664609652,
      "nmse_linear": 0.041360076516866684
    },
    {
      "step_kind": "round",
      "step_index": 2,
      "nmse_db": -15.825969356734655,
      "nmse_linear": 0.026145868003368378
    },
    {
      "step_kind": "round",
      "step_index": 3,
      "nmse_db": -16.52486923381249,
      "nmse_linear": 0.022259380668401718
    },
    {
      "step_kind": "round",
      "step_index": 4,
      "nmse_db": -16.876802402429295,
      "nmse_linear": 0.02052672952413559
    },
    {
      "step_kind": "round",
      "step_index": 5,
      "nmse_db": -17.197095165279727,
      "nmse_linear": 0.01906735636293888
    },
    {
      "step_kind": "round",
      "step_index": 6,
      "nmse_db": -17.503945254336838,
      "nmse_linear": 0.017766647040843964
    },
    {
      "step_kind": "round",
      "step_index": 7,
      "nmse_db": -17.649886718643298,
      "nmse_linear": 0.01717953197658062
    },
    {
      "step_kind": "round",
      "step_index": 8,
      "nmse_db": -17.661278862791747,
      "nmse_linear": 0.0171345267444849
    },
    {
      "step_kind": "round",
      "step_index": 9,
      "nmse_db": -17.77410130386101,
      "nmse_linear": 0.016695132479071617
    },
    {
      "step_kind": "round",
      "step_index": 10,
      "nmse_db": -17.957005004765122,
      "nmse_linear": 0.01600661501288414
    }
  ],
  "summary": {
    "final_nmse_db": -17.957005004765122
  },
  "ended_at": 1776296745.0931041,
  "duration_sec": 97.18721508979797
}